test.py
cfw_proxy/__init__.py
cfw_proxy/certmgr.py
cfw_proxy/cf_proxy.py
cfw_proxy/cli.py
cfw_proxy/http_conn.py
cfw_proxy/http_proxy.py
cfw_proxy/logconfig.py
cfw_proxy2/certmgr.py
cfw_proxy2/cfw_proxy.py
cfw_proxy2/cli.py
cfw_proxy2/http_client.py
cfw_proxy2/http_conn.py
cfw_proxy-1.2.1.dist-info/METADATA
cfw_proxy-1.2.1.dist-info/WHEEL
cfw_proxy-1.2.1.dist-info/entry_points.txt
cfw_proxy-1.2.1.dist-info/top_level.txt
cfw_proxy-1.2.1.dist-info/RECORD
