Metadata-Version: 2.4
Name: cfw-proxy
Version: 1.2.1
Summary: A HTTP proxy server that works with Cloudflare workers
Author-email: Alex Griffin <gg.alexgriffin@gmail.com>
Project-URL: Homepage, https://example.com
Project-URL: Bug Tracker, https://example.com
Classifier: Programming Language :: Python :: 3
Classifier: Operating System :: OS Independent
Requires-Python: >=3.10
Requires-Dist: colorlog
Requires-Dist: cryptography
Requires-Dist: pydantic
Requires-Dist: loguru<0.8,>=0.7.3
